setup.py
viztricks/__init__.py
viztricks/contexts.py
viztricks/convenience.py
viztricks/extensions.py
viztricks/shims.py
viztricks.egg-info/PKG-INFO
viztricks.egg-info/SOURCES.txt
viztricks.egg-info/dependency_links.txt
viztricks.egg-info/requires.txt
viztricks.egg-info/top_level.txt