Metadata-Version: 1.0
Name: viztricks
Version: 0.0.1
Summary: Recipes and helper functions for plotting with Python
Home-page: http://github.com/perimosocordiae/viztricks
Author: CJ Carey
Author-email: perimosocordiae@gmail.com
License: MIT
Platform: UNKNOWN
